inatinqperf/__init__.py
inatinqperf/py.typed
inatinqperf/adaptors/__init__.py
inatinqperf/adaptors/base.py
inatinqperf/adaptors/enums.py
inatinqperf/adaptors/faiss_adaptor.py
inatinqperf/adaptors/milvus_adaptor.py
inatinqperf/adaptors/qdrant_adaptor.py
inatinqperf/adaptors/weaviate_adaptor.py
inatinqperf/benchmark/__init__.py
inatinqperf/benchmark/benchmark.py
inatinqperf/benchmark/configuration.py
inatinqperf/benchmark/container.py
inatinqperf/benchmark/queries.txt
inatinqperf/scripts/pyspy_run.sh
inatinqperf/utils/__init__.py
inatinqperf/utils/dataio.py
inatinqperf/utils/embed.py
inatinqperf/utils/profiler.py
inatinqperf-0.1.70.dist-info/METADATA
inatinqperf-0.1.70.dist-info/WHEEL
inatinqperf-0.1.70.dist-info/licenses/LICENSE
inatinqperf-0.1.70.dist-info/RECORD
