Metadata-Version: 2.4
Name: inatinqperf
Version: 0.1.70
Summary: iNatInqPerf is a benchmark implemented to evalaute performance vs. cost trade-offs of running NLP based search (like INQUIRE) in a platform with different vectorDBs (like INaturalists).
Project-URL: Homepage, https://github.com/gt-sse-center/iNatInqPerf
Project-URL: Documentation, https://github.com/gt-sse-center/iNatInqPerf
Project-URL: Repository, https://github.com/gt-sse-center/iNatInqPerf
Author-email: Ketan Bhardwaj <ketanbj@cc.gatech.edu>
License: MIT
License-File: LICENSE
Classifier: Operating System :: MacOS
Classifier: Operating System :: Microsoft :: Windows
Classifier: Operating System :: POSIX :: Linux
Classifier: Programming Language :: Python
Classifier: Programming Language :: Python :: 3.11
Requires-Python: >=3.10
Requires-Dist: codetiming>=1.4
Requires-Dist: datasets<3.0,>=2.14
Requires-Dist: faiss-cpu>=1.12.0
Requires-Dist: huggingface-hub>=0.23
Requires-Dist: numpy>=2.0.0
Requires-Dist: pandas<2.3,>=1.5
Requires-Dist: pillow>=9.5
Requires-Dist: psutil>=5.9
Requires-Dist: pydantic>=2.11.9
Requires-Dist: pymilvus>=2.6.3
Requires-Dist: pyyaml>=6.0
Requires-Dist: qdrant-client>=1.12.1
Requires-Dist: requests>=2.31
Requires-Dist: safetensors>=0.4
Requires-Dist: simpleeval>=1.0.3
Requires-Dist: tabulate>=0.9.0
Requires-Dist: torch>=2.8.0
Requires-Dist: torchvision>=0.23
Requires-Dist: tqdm>=4.66
Requires-Dist: transformers>=4.53.0
Requires-Dist: typer>=0.17.4
Requires-Dist: weaviate-client>=4.17.0
